zucked.py
zucked-1.0.0.dist-info/LICENSE
zucked-1.0.0.dist-info/METADATA
zucked-1.0.0.dist-info/WHEEL
zucked-1.0.0.dist-info/top_level.txt
zucked-1.0.0.dist-info/RECORD
