Metadata-Version: 2.1
Name: zucked
Version: 1.0.0
Summary: Python library for parsing through facebook messenger data
Home-page: https://github.com/Jordan-Milne/zucked
Author: Jordan Milne
Author-email: jordan.milne2@gmail.com
License: MIT
Download-URL: https://github.com/Jordan-Milne/zucked
Platform: UNKNOWN
Classifier: Development Status :: 4 - Beta
Requires-Python: >=3.6
